django_pursed-0.9.dist-info/DESCRIPTION.rst
django_pursed-0.9.dist-info/LICENSE.txt
django_pursed-0.9.dist-info/METADATA
django_pursed-0.9.dist-info/RECORD
django_pursed-0.9.dist-info/WHEEL
django_pursed-0.9.dist-info/metadata.json
django_pursed-0.9.dist-info/top_level.txt
wallet/__init__.py
wallet/admin.py
wallet/apps.py
wallet/errors.py
wallet/models.py
wallet/views.py
wallet/migrations/0001_initial.py
wallet/migrations/__init__.py
wallet/tests/__init__.py
wallet/tests/test_utils.py
wallet/tests/tests.py
wallet/tests/tests_concurrency.py
